{"paths": {"admin/js/vendor/select2/i18n/pt.js": "admin/js/vendor/select2/i18n/pt.33b4a3b44d43.js", "admin/js/vendor/select2/i18n/hsb.js": "admin/js/vendor/select2/i18n/hsb.fa3b55265efe.js", "admin/js/vendor/select2/i18n/vi.js": "admin/js/vendor/select2/i18n/vi.097a5b75b3e1.js", "admin/js/vendor/select2/i18n/lv.js": "admin/js/vendor/select2/i18n/lv.08e62128eac1.js", "admin/js/vendor/select2/i18n/gl.js": "admin/js/vendor/select2/i18n/gl.d99b1fedaa86.js", "admin/js/vendor/select2/i18n/pl.js": "admin/js/vendor/select2/i18n/pl.6031b4f16452.js", "admin/js/vendor/select2/i18n/el.js": "admin/js/vendor/select2/i18n/el.27097f071856.js", "admin/js/vendor/select2/i18n/dsb.js": "admin/js/vendor/select2/i18n/dsb.56372c92d2f1.js", "admin/js/vendor/select2/i18n/et.js": "admin/js/vendor/select2/i18n/et.2b96fd98289d.js", "admin/js/vendor/select2/i18n/is.js": "admin/js/vendor/select2/i18n/is.3ddd9a6a97e9.js", "admin/js/vendor/select2/i18n/sl.js": "admin/js/vendor/select2/i18n/sl.131a78bc0752.js", "admin/js/vendor/select2/i18n/ko.js": "admin/js/vendor/select2/i18n/ko.e7be6c20e673.js", "admin/js/vendor/select2/i18n/hr.js": "admin/js/vendor/select2/i18n/hr.a2b092cc1147.js", "admin/js/vendor/select2/i18n/ms.js": "admin/js/vendor/select2/i18n/ms.4ba82c9a51ce.js", "admin/js/vendor/select2/i18n/fi.js": "admin/js/vendor/select2/i18n/fi.614ec42aa9ba.js", "admin/js/vendor/select2/i18n/th.js": "admin/js/vendor/select2/i18n/th.f38c20b0221b.js", "admin/js/vendor/select2/i18n/ru.js": "admin/js/vendor/select2/i18n/ru.934aa95f5b5f.js", "admin/js/vendor/select2/i18n/eu.js": "admin/js/vendor/select2/i18n/eu.adfe5c97b72c.js", "admin/js/vendor/select2/i18n/mk.js": "admin/js/vendor/select2/i18n/mk.dabbb9087130.js", "admin/js/vendor/select2/i18n/sq.js": "admin/js/vendor/select2/i18n/sq.5636b60d29c9.js", "admin/js/vendor/select2/i18n/ja.js": "admin/js/vendor/select2/i18n/ja.170ae885d74f.js", "admin/js/vendor/select2/i18n/ka.js": "admin/js/vendor/select2/i18n/ka.2083264a54f0.js", "admin/js/vendor/select2/i18n/he.js": "admin/js/vendor/select2/i18n/he.e420ff6cd3ed.js", "admin/js/vendor/select2/i18n/bg.js": "admin/js/vendor/select2/i18n/bg.39b8be30d4f0.js", "admin/js/vendor/select2/i18n/hy.js": "admin/js/vendor/select2/i18n/hy.c7babaeef5a6.js", "admin/js/vendor/select2/i18n/sr-Cyrl.js": "admin/js/vendor/select2/i18n/sr-Cyrl.f254bb8c4c7c.js", "admin/js/vendor/select2/i18n/ne.js": "admin/js/vendor/select2/i18n/ne.3d79fd3f08db.js", "admin/js/vendor/select2/i18n/af.js": "admin/js/vendor/select2/i18n/af.4f6fcd73488c.js", "admin/js/vendor/select2/i18n/id.js": "admin/js/vendor/select2/i18n/id.04debded514d.js", "admin/js/vendor/select2/i18n/az.js": "admin/js/vendor/select2/i18n/az.270c257daf81.js", "admin/js/vendor/select2/i18n/ca.js": "admin/js/vendor/select2/i18n/ca.a166b745933a.js", "admin/js/vendor/select2/i18n/nb.js": "admin/js/vendor/select2/i18n/nb.da2fce143f27.js", "admin/js/vendor/select2/i18n/zh-CN.js": "admin/js/vendor/select2/i18n/zh-CN.2cff662ec5f9.js", "admin/js/vendor/select2/i18n/zh-TW.js": "admin/js/vendor/select2/i18n/zh-TW.04554a227c2b.js", "admin/js/vendor/select2/i18n/pt-BR.js": "admin/js/vendor/select2/i18n/pt-BR.e1b294433e7f.js", "admin/js/vendor/select2/i18n/da.js": "admin/js/vendor/select2/i18n/da.766346afe4dd.js", "admin/js/vendor/select2/i18n/fa.js": "admin/js/vendor/select2/i18n/fa.3b5bd1961cfd.js", "admin/js/vendor/select2/i18n/de.js": "admin/js/vendor/select2/i18n/de.8a1c222b0204.js", "admin/js/vendor/select2/i18n/en.js": "admin/js/vendor/select2/i18n/en.cf932ba09a98.js", "admin/js/vendor/select2/i18n/bs.js": "admin/js/vendor/select2/i18n/bs.91624382358e.js", "admin/js/vendor/select2/i18n/tk.js": "admin/js/vendor/select2/i18n/tk.7c572a68c78f.js", "admin/js/vendor/select2/i18n/sv.js": "admin/js/vendor/select2/i18n/sv.7a9c2f71e777.js", "admin/js/vendor/select2/i18n/hi.js": "admin/js/vendor/select2/i18n/hi.70640d41628f.js", "admin/js/vendor/select2/i18n/uk.js": "admin/js/vendor/select2/i18n/uk.8cede7f4803c.js", "admin/js/vendor/select2/i18n/cs.js": "admin/js/vendor/select2/i18n/cs.4f43e8e7d33a.js", "admin/js/vendor/select2/i18n/km.js": "admin/js/vendor/select2/i18n/km.c23089cb06ca.js", "admin/js/vendor/select2/i18n/fr.js": "admin/js/vendor/select2/i18n/fr.05e0542fcfe6.js", "admin/js/vendor/select2/i18n/nl.js": "admin/js/vendor/select2/i18n/nl.997868a37ed8.js", "admin/js/vendor/select2/i18n/sr.js": "admin/js/vendor/select2/i18n/sr.5ed85a48f483.js", "admin/js/vendor/select2/i18n/hu.js": "admin/js/vendor/select2/i18n/hu.6ec6039cb8a3.js", "admin/js/vendor/select2/i18n/lt.js": "admin/js/vendor/select2/i18n/lt.23c7ce903300.js", "admin/js/vendor/select2/i18n/ar.js": "admin/js/vendor/select2/i18n/ar.65aa8e36bf5d.js", "admin/js/vendor/select2/i18n/sk.js": "admin/js/vendor/select2/i18n/sk.33d02cef8d11.js", "admin/js/vendor/select2/i18n/it.js": "admin/js/vendor/select2/i18n/it.be4fe8d365b5.js", "admin/js/vendor/select2/i18n/es.js": "admin/js/vendor/select2/i18n/es.66dbc2652fb1.js", "admin/js/vendor/select2/i18n/bn.js": "admin/js/vendor/select2/i18n/bn.6d42b4dd5665.js", "admin/js/vendor/select2/i18n/ro.js": "admin/js/vendor/select2/i18n/ro.f75cb460ec3b.js", "admin/js/vendor/select2/i18n/ps.js": "admin/js/vendor/select2/i18n/ps.38dfa47af9e0.js", "admin/js/vendor/select2/i18n/tr.js": "admin/js/vendor/select2/i18n/tr.b5a0643d1545.js", "admin/css/vendor/select2/select2.min.css": "admin/css/vendor/select2/select2.min.9f54e6414f87.css", "admin/css/vendor/select2/LICENSE-SELECT2.md": "admin/css/vendor/select2/LICENSE-SELECT2.f94142512c91.md", "admin/css/vendor/select2/select2.css": "admin/css/vendor/select2/select2.a2194c262648.css", "admin/js/vendor/jquery/jquery.min.js": "admin/js/vendor/jquery/jquery.min.641dd1437010.js", "admin/js/vendor/jquery/LICENSE.txt": "admin/js/vendor/jquery/LICENSE.de877aa6d744.txt", "admin/js/vendor/jquery/jquery.js": "admin/js/vendor/jquery/jquery.0208b96062ba.js", "admin/js/vendor/xregexp/xregexp.min.js": "admin/js/vendor/xregexp/xregexp.min.b0439563a5d3.js", "admin/js/vendor/xregexp/xregexp.js": "admin/js/vendor/xregexp/xregexp.efda034b9537.js", "admin/js/vendor/xregexp/LICENSE.txt": "admin/js/vendor/xregexp/LICENSE.bf79e414957a.txt", "admin/js/vendor/select2/LICENSE.md": "admin/js/vendor/select2/LICENSE.f94142512c91.md", "admin/js/vendor/select2/select2.full.min.js": "admin/js/vendor/select2/select2.full.min.fcd7500d8e13.js", "admin/js/vendor/select2/select2.full.js": "admin/js/vendor/select2/select2.full.c2afdeda3058.js", "admin/js/admin/RelatedObjectLookups.js": "admin/js/admin/RelatedObjectLookups.9f9bd97ccaa0.js", "admin/js/admin/DateTimeShortcuts.js": "admin/js/admin/DateTimeShortcuts.116c2824468f.js", "admin/js/admin/ordering.js": "admin/js/admin/ordering.8719ee672787.js", "admin/img/gis/move_vertex_on.png": "admin/img/gis/move_vertex_on.99be2571b3f6.png", "admin/img/gis/move_vertex_off.png": "admin/img/gis/move_vertex_off.93ee41d8cad9.png", "admin/img/gis/move_vertex_on.svg": "admin/img/gis/move_vertex_on.0047eba25b67.svg", "admin/img/gis/move_vertex_off.svg": "admin/img/gis/move_vertex_off.7a23bf31ef8a.svg", "admin/css/widgets.css": "admin/css/widgets.6c62aa3b8a2a.css", "admin/css/login.css": "admin/css/login.e51e4c8d6400.css", "admin/css/dashboard.css": "admin/css/dashboard.7e0a4929eabe.css", "admin/css/forms.css": "admin/css/forms.f439c9753a61.css", "admin/css/ie.css": "admin/css/ie.da2e516c7802.css", "admin/css/rtl.css": "admin/css/rtl.bec85fdc28e9.css", "admin/css/base.css": "admin/css/base.c7e0c4edfa7d.css", "admin/css/changelists.css": "admin/css/changelists.4be1d4d486c6.css", "admin/js/LICENSE-JQUERY.txt": "admin/js/LICENSE-JQUERY.3c2025538601.txt", "admin/js/urlify.js": "admin/js/urlify.11f885692a3b.js", "admin/js/inlines.min.js": "admin/js/inlines.min.41a10c2541af.js", "admin/js/core.js": "admin/js/core.97374639b90f.js", "admin/js/collapse.js": "admin/js/collapse.ac25f18141ae.js", "admin/js/actions.js": "admin/js/actions.0f1d7ea3b04a.js", "admin/js/prepopulate.js": "admin/js/prepopulate.575825d0f554.js", "admin/js/jquery.min.js": "admin/js/jquery.min.10092eee563d.js", "admin/js/compress.py": "admin/js/compress.52d3b8fad0d3.py", "admin/js/inlines.js": "admin/js/inlines.cf876c9232ad.js", "admin/js/SelectFilter2.js": "admin/js/SelectFilter2.15c78c79b0ba.js", "admin/js/jquery.init.js": "admin/js/jquery.init.e4f9b321c347.js", "admin/js/SelectBox.js": "admin/js/SelectBox.37509c7e5ad5.js", "admin/js/actions.min.js": "admin/js/actions.min.15856d879af7.js", "admin/js/calendar.js": "admin/js/calendar.73e6c8503401.js", "admin/js/timeparse.js": "admin/js/timeparse.a298a7ede5c3.js", "admin/js/prepopulate.min.js": "admin/js/prepopulate.min.610c44f87c22.js", "admin/js/getElementsBySelector.js": "admin/js/getElementsBySelector.92ac9f95add3.js", "admin/js/collapse.min.js": "admin/js/collapse.min.53fbfa90fde7.js", "admin/js/jquery.js": "admin/js/jquery.c0ac4e323dfd.js", "admin/img/chooser_stacked-bg.gif": "admin/img/chooser_stacked-bg.f5fc6840ea81.gif", "admin/img/chooser-bg.gif": "admin/img/chooser-bg.6d3887744e08.gif", "admin/img/nav-bg-reverse.gif": "admin/img/nav-bg-reverse.aa82f23e9f20.gif", "admin/img/icon_changelink.gif": "admin/img/icon_changelink.76183412227f.gif", "admin/img/deleted-overlay.gif": "admin/img/deleted-overlay.1cd28ce73d7d.gif", "admin/img/tooltag-arrowright.gif": "admin/img/tooltag-arrowright.7868419ed741.gif", "admin/img/icon_searchbox.png": "admin/img/icon_searchbox.562ca64df360.png", "admin/img/icon_alert.gif": "admin/img/icon_alert.572a03fff47e.gif", "admin/img/icon_calendar.gif": "admin/img/icon_calendar.b4704fc81e9d.gif", "admin/img/selector-icons.gif": "admin/img/selector-icons.4549da0d5c7f.gif", "admin/img/nav-bg-grabber.gif": "admin/img/nav-bg-grabber.45d7c744bbe8.gif", "admin/img/icon-yes.gif": "admin/img/icon-yes.0596085e212f.gif", "admin/img/inline-delete.png": "admin/img/inline-delete.2fbde56e39ec.png", "admin/img/tooltag-arrowright_over.gif": "admin/img/tooltag-arrowright_over.05e21ca7df0a.gif", "admin/img/tool-left_over.gif": "admin/img/tool-left_over.dd6b2c9741ae.gif", "admin/img/default-bg-reverse.gif": "admin/img/default-bg-reverse.5db23944ca5c.gif", "admin/img/selector-search.gif": "admin/img/selector-search.a5de786630be.gif", "admin/img/inline-restore.png": "admin/img/inline-restore.8c51d7ca1a0b.png", "admin/img/icon_success.gif": "admin/img/icon_success.08e6b9d922e1.gif", "admin/img/icon-unknown.gif": "admin/img/icon-unknown.662022bb6ab0.gif", "admin/img/sorting-icons.gif": "admin/img/sorting-icons.2a27f8855e6b.gif", "admin/img/changelist-bg.gif": "admin/img/changelist-bg.47aed546eec8.gif", "admin/img/inline-splitter-bg.gif": "admin/img/inline-splitter-bg.40be0ed80875.gif", "admin/img/tool-left.gif": "admin/img/tool-left.ecf10ae8cb84.gif", "admin/img/tooltag-add_over.gif": "admin/img/tooltag-add_over.fd06851536ae.gif", "admin/img/icon_addlink.gif": "admin/img/icon_addlink.27872b1581c4.gif", "admin/img/tool-right_over.gif": "admin/img/tool-right_over.bb1e38144ccd.gif", "admin/img/changelist-bg_rtl.gif": "admin/img/changelist-bg_rtl.db38ab536edc.gif", "admin/img/nav-bg.gif": "admin/img/nav-bg.dc7bc05b7ef1.gif", "admin/img/inline-restore-8bit.png": "admin/img/inline-restore-8bit.600f948fd1e0.png", "admin/img/icon_clock.gif": "admin/img/icon_clock.d65ba15015dd.gif", "admin/img/tooltag-add.gif": "admin/img/tooltag-add.0e639fd18a0e.gif", "admin/img/nav-bg-selected.gif": "admin/img/nav-bg-selected.4ebddc881b37.gif", "admin/img/icon_deletelink.gif": "admin/img/icon_deletelink.b797f0120322.gif", "admin/img/icon-no.gif": "admin/img/icon-no.2888642640a3.gif", "admin/img/tool-right.gif": "admin/img/tool-right.f5114f1303e9.gif", "admin/img/icon_error.gif": "admin/img/icon_error.d0272cd88394.gif", "admin/img/default-bg.gif": "admin/img/default-bg.e61a71c9e730.gif", "admin/img/inline-delete-8bit.png": "admin/img/inline-delete-8bit.948cb0fe0c16.png", "admin/css/dark_mode.css": "admin/css/dark_mode.ef27a31af300.css", "admin/css/nav_sidebar.css": "admin/css/nav_sidebar.269a1bd44627.css", "admin/css/responsive.css": "admin/css/responsive.f6533dab034d.css", "admin/css/autocomplete.css": "admin/css/autocomplete.4a81fc4242d0.css", "admin/css/responsive_rtl.css": "admin/css/responsive_rtl.7d1130848605.css", "admin/js/cancel.js": "admin/js/cancel.ecc4c5ca7b32.js", "admin/js/theme.js": "admin/js/theme.ab270f56bb9c.js", "admin/js/nav_sidebar.js": "admin/js/nav_sidebar.3b9190d420b1.js", "admin/js/autocomplete.js": "admin/js/autocomplete.01591ab27be7.js", "admin/js/change_form.js": "admin/js/change_form.9d8ca4f96b75.js", "admin/js/filters.js": "admin/js/filters.0e360b7a9f80.js", "admin/js/popup_response.js": "admin/js/popup_response.c6cc78ea5551.js", "admin/js/prepopulate_init.js": "admin/js/prepopulate_init.6cac7f3105b8.js", "admin/img/search.svg": "admin/img/search.7cf54ff789c6.svg", "admin/img/icon-calendar.svg": "admin/img/icon-calendar.ac7aea671bea.svg", "admin/img/icon-clock.svg": "admin/img/icon-clock.e1d4dfac3f2b.svg", "admin/img/icon-no.svg": "admin/img/icon-no.439e821418cd.svg", "admin/img/tooltag-add.svg": "admin/img/tooltag-add.e59d620a9742.svg", "admin/img/inline-delete.svg": "admin/img/inline-delete.fec1b761f254.svg", "admin/img/LICENSE": "admin/img/LICENSE.2c54f4e1ca1c", "admin/img/icon-changelink.svg": "admin/img/icon-changelink.18d2fd706348.svg", "admin/img/icon-unknown.svg": "admin/img/icon-unknown.a18cb4398978.svg", "admin/img/sorting-icons.svg": "admin/img/sorting-icons.3a097b59f104.svg", "admin/img/icon-viewlink.svg": "admin/img/icon-viewlink.41eb31f7826e.svg", "admin/img/icon-yes.svg": "admin/img/icon-yes.d2f9f035226a.svg", "admin/img/icon-addlink.svg": "admin/img/icon-addlink.d519b3bab011.svg", "admin/img/icon-unknown-alt.svg": "admin/img/icon-unknown-alt.81536e128bb6.svg", "admin/img/icon-deletelink.svg": "admin/img/icon-deletelink.564ef9dc3854.svg", "admin/img/README.txt": "admin/img/README.a70711a38d87.txt", "admin/img/selector-icons.svg": "admin/img/selector-icons.b4555096cea2.svg", "admin/img/calendar-icons.svg": "admin/img/calendar-icons.39b290681a8b.svg", "admin/img/tooltag-arrowright.svg": "admin/img/tooltag-arrowright.bbfb788a849e.svg", "admin/img/icon-alert.svg": "admin/img/icon-alert.034cc7d8a67f.svg", "js/bootstrap.min.js": "js/bootstrap.min.26412a9ee704.js", "sounds/theme.mp3": "sounds/theme.87f7d1d7972b.mp3", "font/fontawesome-webfont.svg": "font/fontawesome-webfont.b8e4dbe6872f.svg", "font/FontAwesome.otf": "font/FontAwesome.59dc59981f82.otf", "font/SIL Open Font License.txt": "font/SIL Open Font License.cfbfbc6c1e09.txt", "font/AlexBrush-Regular.ttf": "font/AlexBrush-Regular.c8b7ff20d0c0.ttf", "font/fontawesome-webfont.ttf": "font/fontawesome-webfont.bb72c5142ae2.ttf", "font/fontawesome-webfont.woff": "font/fontawesome-webfont.21f212f94a9d.woff", "font/Amble-Regular-webfont.ttf": "font/Amble-Regular-webfont.b9ce87c31ce1.ttf", "font/fontawesome-webfont.eot": "font/fontawesome-webfont.455808250694.eot", "fonts/Antonio-Regular.ttf": "fonts/Antonio-Regular.25cd38a8b03f.ttf", "fonts/MonsOlympia.ttf": "fonts/MonsOlympia.45a8f7433598.ttf", "fonts/moto-verse.ttf": "fonts/moto-verse.09d2c74644ae.ttf", "fonts/MonsOlympiaCondensed.ttf": "fonts/MonsOlympiaCondensed.3e1c305978ec.ttf", "fonts/ethnocentric_rg.otf": "fonts/ethnocentric_rg.a3b1643f5b47.otf", "Assets/questionbox.jpg": "Assets/questionbox.f6cf75b69e3a.jpg", "Assets/techbairn.png": "Assets/techbairn.77d92544d408.png", "Assets/techbairn.jpg": "Assets/techbairn.4a93d7bf45d3.jpg", "Assets/hdesk.webp": "Assets/hdesk.8c251c94b04d.webp", "Assets/isteLogoThemed.png": "Assets/isteLogoThemed.b52cd8d8f57e.png", "Assets/title.png": "Assets/title.01fe936e6df4.png", "Assets/image 11.png": "Assets/image 11.574a6ddacd3e.png", "Assets/bg-portrait.png": "Assets/bg-portrait.5f74e2f37edc.png", "Assets/question.png": "Assets/question.bce332970fa8.png", "Assets/Asset 3.png": "Assets/Asset 3.89a9563f5b27.png", "Assets/istei.jpeg": "Assets/istei.36751ab628b9.jpeg", "Assets/brain.png": "Assets/brain.d5f7a0615e22.png", "Assets/bg.webp": "Assets/bg.c2e78dfb458e.webp", "Assets/Asset 2.png": "Assets/Asset 2.ad74b2c3f210.png", "Assets/logout.png": "Assets/logout.0b6c33804e14.png", "Assets/Asset 1.png": "Assets/Asset 1.929eb8c79e98.png", "Assets/Rectangle 2.png": "Assets/Rectangle 2.df7e6aefbbaf.png", "Assets/linkedin_1377213 - Copy.png": "Assets/linkedin_1377213 - Copy.59d2da8a4cc1.png", "Assets/ims.png": "Assets/ims.fe7328b8d4ae.png", "Assets/ims.jpg": "Assets/ims.e62655e27d1b.jpg", "Assets/hmobile.webp": "Assets/hmobile.2d9bd57a0eb5.webp", "Assets/Untitled-1-01.png": "Assets/Untitled-1-01.b52cd8d8f57e.png", "Assets/logoThemed.png": "Assets/logoThemed.b52cd8d8f57e.png", "Assets/student.png": "Assets/student.84e2b7980260.png", "Assets/man1.jpg": "Assets/man1.f246bb77c9af.jpg", "Assets/Enter.png": "Assets/Enter.849e560cfabf.png", "Assets/whiteIste.png": "Assets/whiteIste.56e1483e2436.png", "Assets/lboard1.png": "Assets/lboard1.aef787fe5bad.png", "Assets/bgp.png": "Assets/bgp.6aa9fc6ba68e.png", "Assets/LboardAsset1.svg": "Assets/LboardAsset1.17f6bdf4a041.svg", "Assets/whiteIste (1).png": "Assets/whiteIste (1).953f935cb361.png", "Assets/schedule.jpg": "Assets/schedule.c77147febe9f.jpg", "Assets/profile.png": "Assets/profile.6e697a1615d3.png", "Assets/LboardAsset3.svg": "Assets/LboardAsset3.f6748b23f843.svg", "Assets/dotsBg.png": "Assets/dotsBg.5b6520bf8f55.png", "Assets/homePageMobile.webp": "Assets/homePageMobile.f7c82e9e698f.webp", "Assets/twitter_3955031 - Copy.png": "Assets/twitter_3955031 - Copy.00e1685acb78.png", "Assets/LboardAsset2.svg": "Assets/LboardAsset2.47a3042ec2a8.svg", "Assets/monkey.jpg": "Assets/monkey.4f7c3fcfe121.jpg", "Assets/heroimg.jpg": "Assets/heroimg.64bca73f140a.jpg", "Assets/Untitled.png": "Assets/Untitled.201f3b8f2f4b.png", "Assets/aboutbg.jpg": "Assets/aboutbg.1fb8573aec80.jpg", "Assets/prizesbg.jpg": "Assets/prizesbg.bc3bb0104239.jpg", "Assets/hdesk.png": "Assets/hdesk.6e7be57bb792.png", "Assets/bg25latest.png": "Assets/bg25latest.d717418a4a39.png", "Assets/pic.jpg": "Assets/pic.b628965a2d69.jpg", "Assets/homePageDesktop.webp": "Assets/homePageDesktop.792fb6d8205d.webp", "Assets/iocl.png": "Assets/iocl.0cd8bdd2df8c.png", "Assets/sectionno.jpg": "Assets/sectionno.b96dbcfb688a.jpg", "Assets/instagram_408758.png": "Assets/instagram_408758.eb8f7feedb9f.png", "Assets/social_13480297.png": "Assets/social_13480297.1ca6a025e489.png", "Assets/iste-logo.png": "Assets/iste-logo.56e1483e2436.png", "Assets/tech.png": "Assets/tech.6af1f0792781.png", "Assets/ims copy.png": "Assets/ims copy.8b4102157f7a.png", "Assets/bg.png": "Assets/bg.948d70e8cfc1.png", "Assets/hmobile.png": "Assets/hmobile.05e251ca437e.png"}, "version": "1.1", "hash": "f8c54f01808b"}